class_resolver/__init__.py
class_resolver/api.py
class_resolver/base.py
class_resolver/contrib/__init__.py
class_resolver/contrib/numpy.py
class_resolver/contrib/optuna.py
class_resolver/contrib/sklearn.py
class_resolver/contrib/torch.py
class_resolver/contrib/torch_geometric.py
class_resolver/docs.py
class_resolver/func.py
class_resolver/py.typed
class_resolver/utils.py
class_resolver/version.py
class_resolver-0.7.0.dist-info/licenses/LICENSE
class_resolver-0.7.0.dist-info/WHEEL
class_resolver-0.7.0.dist-info/entry_points.txt
class_resolver-0.7.0.dist-info/METADATA
class_resolver-0.7.0.dist-info/RECORD
