Metadata-Version: 2.4
Name: class-resolver
Version: 0.7.0
Summary: Lookup and instantiate classes with style.
Keywords: snekpack,cookiecutter,development tool,configurability
Author: Charles Tapley Hoyt
Author-email: Charles Tapley Hoyt <cthoyt@gmail.com>
License-File: LICENSE
Classifier: Development Status :: 5 - Production/Stable
Classifier: Environment :: Console
Classifier: Intended Audience :: Developers
Classifier: License :: OSI Approved :: MIT License
Classifier: Operating System :: OS Independent
Classifier: Framework :: Pytest
Classifier: Framework :: tox
Classifier: Framework :: Sphinx
Classifier: Natural Language :: English
Classifier: Programming Language :: Python
Classifier: Programming Language :: Python :: 3.10
Classifier: Programming Language :: Python :: 3.11
Classifier: Programming Language :: Python :: 3.12
Classifier: Programming Language :: Python :: 3.13
Classifier: Programming Language :: Python :: 3 :: Only
Classifier: Typing :: Typed
Requires-Dist: typing-extensions
Requires-Dist: click>=8.2 ; extra == 'click'
Requires-Dist: numpy ; extra == 'numpy'
Requires-Dist: optuna ; extra == 'optuna'
Requires-Dist: scikit-learn ; extra == 'sklearn'
Requires-Dist: tabulate ; extra == 'tabulate'
Requires-Dist: torch ; extra == 'torch'
Requires-Dist: torch ; extra == 'torch-geometric'
Requires-Dist: torch-sparse ; extra == 'torch-geometric'
Requires-Dist: torch-geometric ; extra == 'torch-geometric'
Maintainer: Charles Tapley Hoyt
Maintainer-email: Charles Tapley Hoyt <cthoyt@gmail.com>
Requires-Python: >=3.10
Project-URL: Bug Tracker, https://github.com/cthoyt/class-resolver/issues
Project-URL: Documentation, https://class_resolver.readthedocs.io
Project-URL: Funding, https://github.com/sponsors/cthoyt
Project-URL: Homepage, https://github.com/cthoyt/class-resolver
Project-URL: Repository, https://github.com/cthoyt/class-resolver.git
Provides-Extra: click
Provides-Extra: numpy
Provides-Extra: optuna
Provides-Extra: sklearn
Provides-Extra: tabulate
Provides-Extra: torch
Provides-Extra: torch-geometric
